graphql_scalars/__init__.py
graphql_scalars/scalars/__init__.py
graphql_scalars/scalars/date_time.py
graphql_scalars/scalars/json.py
graphql_scalars/scalars/timestamp.py
graphql_scalars/scalars/void.py
graphql_scalars/settings.py
graphql_scalars/types.py
graphql_scalars-0.2.4.dist-info/LICENSE
graphql_scalars-0.2.4.dist-info/WHEEL
graphql_scalars-0.2.4.dist-info/METADATA
graphql_scalars-0.2.4.dist-info/RECORD
