Metadata-Version: 2.1
Name: graphql-scalars
Version: 0.2.4
Summary: A library of custom GraphQL scalar types for creating precise type-safe GraphQL schemas.
License: MIT
Author: iyanging
Author-email: iyanging@163.com
Requires-Python: >=3.9,<3.10
Classifier: License :: OSI Approved :: MIT License
Classifier: Programming Language :: Python :: 3
Classifier: Programming Language :: Python :: 3.9
Requires-Dist: arrow (>=1.1.0,<1.2.0)
Requires-Dist: graphql-core (>=3.1.4,<3.2.0)
